rtl/charge_controller.v
module charge_controller (
    input wire clk,
    input wire rst,
    input wire [7:0] v_batt,
    input wire temp_high,
    input wire charger_plugged,

    output reg charge_en,
    output reg alert_led
);
    parameter IDLE    = 3'b000;
    parameter CC_MODE = 3'b001;
    parameter CV_MODE = 3'b010;
    parameter FULL    = 3'b011;
    parameter FAULT   = 3'b100;

    reg [2:0] current_state, next_state;

    always @(posedge clk or posedge rst) begin
        if(rst)
            current_state <= IDLE;
        else
            current_state <= next_state;
    end

    always @(*) begin
        next_state = current_state;
        charge_en = 1'b0;
        alert_led = 1'b0;

        if(temp_high) begin
            next_state = FAULT;
        end else begin
            case(current_state)
                IDLE: begin
                    charge_en = 1'b0;
                    if(charger_plugged) begin
                        next_state = CC_MODE;
                    end
                end

                CC_MODE: begin
                    charge_en = 1'b1;
                    if(v_batt >= 8'd200) begin
                        next_state = CV_MODE;
                    end
                end

                CV_MODE: begin
                    charge_en = 1'b1;
                    if(v_batt >= 8'd255) begin
                        next_state = FULL;
                    end
                end

                FULL: begin 
                    charge_en = 1'b0;
                    if(charger_plugged == 1'b0) begin
                        next_state = IDLE;
                    end
                end

                FAULT: begin
                    charge_en = 1'b0;
                    alert_led = 1'b1;
                    if(charger_plugged == 1'b0 && temp_high == 1'b0) begin
                        next_state = IDLE;
                    end
                end

                default: next_state = IDLE;
            endcase
        end
    end
endmodule

sim/tb_charge_controller.v
`timescale 1ns / 1ps

module tb_charge_controller();

    reg clk;
    reg rst;
    reg [7:0] v_batt;
    reg temp_high;
    reg charger_plugged;

    wire charge_en;
    wire alert_led;

    charge_controller uut (
        .clk(clk),
        .rst(rst),
        .v_batt(v_batt),
        .temp_high(temp_high),
        .charger_plugged(charger_plugged),
        .charge_en(charge_en),
        .alert_led(alert_led)
    );

    always #5 clk = ~clk;

    initial begin
        $dumpfile("simulation.vcd");
        $dumpvars(0, tb_charge_controller);

      
        $display("--- BAT DAU KIEM CHUNG ---");
        clk = 0; rst = 1; v_batt = 8'd0; temp_high = 0; charger_plugged = 0;
        #15 rst = 0; 
        $display("[%0t] Khoi dong xong. Trang thai IDLE.", $time);

        #10 charger_plugged = 1; v_batt = 8'd100; 
        $display("[%0t] Cam sac (v_batt=100) -> Chuyen CC_MODE", $time);

        #30 v_batt = 8'd210; 
        $display("[%0t] Pin vuot nguong 200 (v_batt=210) -> Chuyen CV_MODE", $time);

        #30 v_batt = 8'd255; 
        $display("[%0t] Pin day (v_batt=255) -> Chuyen FULL", $time);

        #20 charger_plugged = 0; 
        $display("[%0t] Rut sac -> Ve lai IDLE", $time);

       
        #30 charger_plugged = 1; v_batt = 8'd150; 
        $display("[%0t] Cam sac lai. Dang CC_MODE...", $time);

        #20 temp_high = 1; 
        $display("[%0t] CANH BAO! Qua nhiet! -> Nhay sang FAULT, Ngat sac, Bat LED", $time);

        #30 charger_plugged = 0; 
        $display("[%0t] Da rut sac nhung van nong -> Van giu FAULT", $time);

        #30 temp_high = 0; 
        $display("[%0t] Nhiet do on dinh tro lai -> Ve IDLE", $time);

     
        #50 $display("--- KET THUC KIEM CHUNG ---");
        $finish;
    end

endmodule

sim/simulation.vcd
$date
	Wed Aug 26 21:14:24 2026
$end
$version
	Icarus Verilog
$end
$timescale
	1ps
$end
$scope module tb_charge_controller $end
$var wire 1 ! charge_en $end
$var wire 1 " alert_led $end
$var reg 1 # charger_plugged $end
$var reg 1 $ clk $end
$var reg 1 % rst $end
$var reg 1 & temp_high $end
$var reg 8 ' v_batt [7:0] $end
$scope module uut $end
$var wire 1 # charger_plugged $end
$var wire 1 $ clk $end
$var wire 1 % rst $end
$var wire 1 & temp_high $end
$var wire 8 ( v_batt [7:0] $end
$var parameter 3 ) CC_MODE $end
$var parameter 3 * CV_MODE $end
$var parameter 3 + FAULT $end
$var parameter 3 , FULL $end
$var parameter 3 - IDLE $end
$var reg 1 " alert_led $end
$var reg 1 ! charge_en $end
$var reg 3 . current_state [2:0] $end
$var reg 3 / next_state [2:0] $end
$upscope $end
$upscope $end
$enddefinitions $end
$comment Show the parameter values. $end
$dumpall
b0 -
b11 ,
b100 +
b10 *
b1 )
$end
#0
$dumpvars
b0 /
b0 .
b0 (
b0 '
0&
1%
0$
0#
0"
0!
$end
#5000
1$
#10000
0$
#15000
1$
0%
#20000
0$
#25000
1!
b1 .
b1 /
1$
b1100100 '
b1100100 (
1#
#30000
0$
#35000
1$
#40000
0$
#45000
1$
#50000
0$
#55000
b10 .
b10 /
1!
1$
b11010010 '
b11010010 (
#60000
0$
#65000
1$
#70000
0$
#75000
1$
#80000
0$
#85000
b11 .
b11 /
0!
1$
b11111111 '
b11111111 (
#90000
0$
#95000
1$
#100000
0$
#105000
b0 .
b0 /
1$
0#
#110000
0$
#115000
1$
#120000
0$
#125000
1$
#130000
0$
#135000
1!
b1 .
b1 /
1$
b10010110 '
b10010110 (
1#
#140000
0$
#145000
1$
#150000
0$
#155000
b100 .
b100 /
0!
1$
1&
#160000
0$
#165000
1$
#170000
0$
#175000
1$
#180000
0$
#185000
1$
0#
#190000
0$
#195000
1$
#200000
0$
#205000
1$
#210000
0$
#215000
b0 .
b0 /
0"
1$
0&
